Metadata-Version: 2.1
Name: vocalist
Version: 0.0.1.dev0
Summary: A package to convert speech to long-form work-flows, using plugable trained NLP models
Home-page: UNKNOWN
Author: Colin Lacy
Author-email: colinjlacy@gmail.com
License: UNKNOWN
Platform: UNKNOWN
Classifier: Programming Language :: Python :: 3.6
Classifier: License :: OSI Approved :: GNU General Public License v3 (GPLv3)
